openintel/__init__.py
openintel/analyzer.py
openintel/cli.py
openintel/detector.py
openintel/models.py
openintel/signatures.py
openintel-1.0.0.dist-info/METADATA
openintel-1.0.0.dist-info/WHEEL
openintel-1.0.0.dist-info/entry_points.txt
openintel-1.0.0.dist-info/licenses/LICENSE
openintel-1.0.0.dist-info/RECORD
