Metadata-Version: 2.4
Name: openintel
Version: 1.0.0
Summary: A comprehensive tool to detect technology stacks used by websites
Project-URL: Homepage, https://github.com/Devanshusisodiya/openintel
Project-URL: Repository, https://github.com/Devanshusisodiya/openintel
Project-URL: Issues, https://github.com/Devanshusisodiya/openintel/issues
Author-email: Devanshu Singh <devanshukumar45@gmail.com>
License-Expression: MIT
License-File: LICENSE
Keywords: competitive-intelligence,mixrank,technology-detection,web-scraping
Classifier: Development Status :: 4 - Beta
Classifier: Intended Audience :: Developers
Classifier: License :: OSI Approved :: MIT License
Classifier: Operating System :: OS Independent
Classifier: Programming Language :: Python :: 3
Classifier: Programming Language :: Python :: 3.8
Classifier: Programming Language :: Python :: 3.9
Classifier: Programming Language :: Python :: 3.10
Classifier: Programming Language :: Python :: 3.11
Classifier: Programming Language :: Python :: 3.12
Classifier: Topic :: Internet :: WWW/HTTP
Classifier: Topic :: Software Development :: Libraries :: Python Modules
Requires-Python: >=3.8
Requires-Dist: aiohttp>=3.8.0
Requires-Dist: beautifulsoup4>=4.11.0
Requires-Dist: dnspython>=2.2.0
Requires-Dist: requests>=2.28.0
Requires-Dist: typing-extensions>=4.0.0
Provides-Extra: dev
Requires-Dist: coverage>=7.0.0; extra == 'dev'
Requires-Dist: mypy>=1.0.0; extra == 'dev'
Requires-Dist: pytest-asyncio>=0.20.0; extra == 'dev'
Requires-Dist: pytest>=7.0.0; extra == 'dev'
Requires-Dist: ruff>=0.1.0; extra == 'dev'
